densenet_pytorch/__init__.py
densenet_pytorch/model.py
densenet_pytorch/utils.py
densenet_pytorch-0.2.0.dist-info/LICENSE
densenet_pytorch-0.2.0.dist-info/METADATA
densenet_pytorch-0.2.0.dist-info/WHEEL
densenet_pytorch-0.2.0.dist-info/top_level.txt
densenet_pytorch-0.2.0.dist-info/RECORD
