Metadata-Version: 2.1
Name: densenet-pytorch
Version: 0.2.0
Summary: Restore the official code 100% and improve it to make it easier to research and facilitate production.
Home-page: https://github.com/Lornatang/DenseNet-PyTorch
Author: Liu Changyu
Author-email: liuchangyu1111@gmail.com
License: Apache
Platform: UNKNOWN
Classifier: License :: OSI Approved :: Apache Software License
Classifier: Programming Language :: Python
Classifier: Programming Language :: Python :: 3
Classifier: Programming Language :: Python :: 3.6
Classifier: Programming Language :: Python :: 3.7
Requires-Python: >=3.6.0
Requires-Dist: torch
